netfoundry/__init__.py
netfoundry/_version.py
netfoundry/base.py
netfoundry/ctl.py
netfoundry/demo.py
netfoundry/exceptions.py
netfoundry/logger_base.py
netfoundry/network.py
netfoundry/network_group.py
netfoundry/organization.py
netfoundry/table_lexer.py
netfoundry/utility.py
netfoundry/version.py
netfoundry/friendly-words/.gitignore
netfoundry/friendly-words/.glitch-assets
netfoundry/friendly-words/CODE_OF_CONDUCT.md
netfoundry/friendly-words/CONTRIBUTING.md
netfoundry/friendly-words/LICENSE.md
netfoundry/friendly-words/README.md
netfoundry/friendly-words/generated/words.json
netfoundry/friendly-words/words/collections.txt
netfoundry/friendly-words/words/objects.txt
netfoundry/friendly-words/words/predicates.txt
netfoundry/friendly-words/words/teams.txt
netfoundry-5.11.3.dist-info/licenses/LICENSE.txt
netfoundry-5.11.3.dist-info/METADATA
netfoundry-5.11.3.dist-info/WHEEL
netfoundry-5.11.3.dist-info/entry_points.txt
netfoundry-5.11.3.dist-info/top_level.txt
netfoundry-5.11.3.dist-info/RECORD
