Metadata-Version: 2.4
Name: netfoundry
Version: 5.11.3
Summary: Interface to the NetFoundry network-as-code orchestration platform
Author: Kenneth Bingham
Author-email: kenneth.bingham@netfoundry.io
Maintainer: NetFoundry
Maintainer-email: support@netfoundry.io
License: MIT
Project-URL: Documentation, https://developer.netfoundry.io/guides/python/
Project-URL: Source, https://github.com/netfoundry/python-netfoundry/
Project-URL: Tracker, https://github.com/netfoundry/python-netfoundry/issues
Classifier: Programming Language :: Python :: 3
Classifier: Operating System :: OS Independent
Requires-Python: >=3.7
License-File: LICENSE.txt
Requires-Dist: inflect>=5.3
Requires-Dist: milc>=1.8.0
Requires-Dist: packaging>=20.9
Requires-Dist: platformdirs>=2.4
Requires-Dist: pygments>=2.11
Requires-Dist: pyjwt>=2.3
Requires-Dist: pyyaml>=5.4
Requires-Dist: requests>=2.30
Requires-Dist: tabulate>=0.8
Requires-Dist: requests-cache>=0.9.4
Dynamic: license-file
